{
  "main": {
    "id": "55d594a3f41ff89d",
    "type": "split",
    "children": [
      {
        "id": "07f80c6522e29aef",
        "type": "tabs",
        "children": [
          {
            "id": "551094fceb3a979c",
            "type": "leaf",
            "state": {
              "type": "empty",
              "state": {}
            }
          }
        ]
      }
    ],
    "direction": "vertical"
  },
  "left": {
    "id": "d106516995144f9f",
    "type": "split",
    "children": [
      {
        "id": "ddfdc6e9f2e0e5b7",
        "type": "tabs",
        "children": [
          {
            "id": "1d454da9672a5f94",
            "type": "leaf",
            "state": {
              "type": "file-explorer",
              "state": {
                "sortOrder": "alphabetical"
              }
            }
          },
          {
            "id": "873add9ce59de944",
            "type": "leaf",
            "state": {
              "type": "search",
              "state": {
                "query": "",
                "matchingCase": false,
                "explainSearch": false,
                "collapseAll": false,
                "extraContext": false,
                "sortOrder": "alphabetical"
              }
            }
          },
          {
            "id": "b453f8ce88115ced",
            "type": "leaf",
            "state": {
              "type": "starred",
              "state": {}
            }
          }
        ]
      }
    ],
    "direction": "horizontal",
    "width": 300
  },
  "right": {
    "id": "de85a1cb2bb094c6",
    "type": "split",
    "children": [
      {
        "id": "3f7081eabde2647b",
        "type": "tabs",
        "children": [
          {
            "id": "3faa64a994a6cbf9",
            "type": "leaf",
            "state": {
              "type": "calendar",
              "state": {}
            }
          },
          {
            "id": "2b291cf32aab4dea",
            "type": "leaf",
            "state": {
              "type": "backlink",
              "state": {
                "collapseAll": false,
                "extraContext": false,
                "sortOrder": "alphabetical",
                "showSearch": false,
                "searchQuery": "",
                "backlinkCollapsed": false,
                "unlinkedCollapsed": true
              }
            }
          },
          {
            "id": "9e5c4f771e773132",
            "type": "leaf",
            "state": {
              "type": "outgoing-link",
              "state": {
                "linksCollapsed": false,
                "unlinkedCollapsed": true
              }
            }
          },
          {
            "id": "6e6d084b582f6453",
            "type": "leaf",
            "state": {
              "type": "tag",
              "state": {
                "sortOrder": "frequency",
                "useHierarchy": true
              }
            }
          },
          {
            "id": "ee807f8d2dfb6e55",
            "type": "leaf",
            "state": {
              "type": "outline",
              "state": {}
            }
          },
          {
            "id": "2eaa5b9d11a9c722",
            "type": "leaf",
            "state": {
              "type": "todo",
              "state": {}
            }
          },
          {
            "id": "45009b38e1e7c675",
            "type": "leaf",
            "state": {
              "type": "advanced-tables-toolbar",
              "state": {}
            }
          }
        ],
        "currentTab": 6
      }
    ],
    "direction": "horizontal",
    "width": 370.5,
    "collapsed": true
  },
  "left-ribbon": {
    "hiddenItems": {
      "table-editor-obsidian:Advanced Tables Toolbar": false,
      "templater-obsidian:Templater": false,
      "switcher:Open quick switcher": false,
      "graph:Open graph view": false,
      "canvas:Create new canvas": false,
      "daily-notes:Open today's daily note": false,
      "templates:Insert template": false,
      "command-palette:Open command palette": false,
      "markdown-importer:Open format converter": false,
      "random-note:Open random note": false,
      "audio-recorder:Start/stop recording": false
    }
  },
  "floating": {
    "id": "adab02b7974982e7",
    "type": "floating",
    "children": [
      {
        "id": "0464ad317d257f35",
        "type": "window",
        "children": [
          {
            "id": "c1b19c0a1b58ee02",
            "type": "tabs",
            "children": [
              {
                "id": "3f15b4c0e0d3447d",
                "type": "leaf",
                "state": {
                  "type": "markdown",
                  "state": {
                    "file": "Old Notes/World Notes - Old/Non Material Planes/Non-Material Planes.md",
                    "mode": "source",
                    "source": false
                  }
                }
              }
            ]
          }
        ],
        "direction": "vertical",
        "x": 476,
        "y": 134,
        "width": 1024,
        "height": 800,
        "maximize": true,
        "zoom": 0
      }
    ]
  },
  "active": "551094fceb3a979c",
  "lastOpenFiles": [
    "conflict-files-obsidian-git.md",
    "World Mythology.md",
    "To Do.md",
    "Campaign Ideas.md",
    "Old Notes/Scenario 1 - Where's Mommy.md",
    "README.md",
    "Race_Tree.canvas",
    "Old Notes/OG Avenon.svg",
    "Avenon Map.svg",
    "Old Notes/Avenon 2023-02-11-21-26.svg"
  ]
}